{
    "played_tracks": [
        {
            "id": "0lizgQ7Qw35od7CYaoMBZb",
            "name": "Santa Tell Me",
            "artist": "Ariana Grande"
        },
        {
            "id": "2bCCJgTeIkO4BYqGoH2sPB",
            "name": "Stille Nacht",
            "artist": "Kinderliedjes, Kerstliedjes Band"
        },
        {
            "id": "0bYg9bo50gSsH3LtXe2SQn",
            "name": "All I Want for Christmas Is You",
            "artist": "Mariah Carey"
        },
        {
            "id": "5UGAN5uZ8ic270gLaPaFBY",
            "name": "Santa Claus Is Comin' to Town",
            "artist": "Bruce Springsteen"
        },
        {
            "id": "1dSuhAiBjsrsUDzRsLKR3T",
            "name": "Let It Snow",
            "artist": "De Staat"
        },
        {
            "id": "0QtJZpyfZF67QF32p41NXa",
            "name": "Thank God It's Christmas",
            "artist": "Queen"
        },
        {
            "id": "2IuUMx3uxxJAHcH41aYtn0",
            "name": "Winter Wonderland - Remastered 2006",
            "artist": "Bing Crosby"
        },
        {
            "id": "3ma7iAKJCYYIkNEjAmIyBA",
            "name": "Being Alone At Christmas",
            "artist": "Miss Montreal"
        },
        {
            "id": "4hAkwE0k1MlzDoOIf9J8ty",
            "name": "Happy Xmas (War Is Over)",
            "artist": "John Lennon, The Plastic Ono Band, The Harlem Community Choir"
        },
        {
            "id": "2FRnf9qhLbvw8fu4IBXx78",
            "name": "Last Christmas",
            "artist": "Wham!"
        },
        {
            "id": "2SpxCxwl7naL1IkcK1FlCU",
            "name": "Ho Ho Ho",
            "artist": "De Jeugd Van Tegenwoordig, Katja Schuurman"
        },
        {
            "id": "66GRZWDfGCXCYql07FNZjk",
            "name": "Het Is Pas Echt Kerstmis (Als Mariah Carey Op De Radio Is)",
            "artist": "Vrienden Van De Frank En Vrijdag Show"
        },
        {
            "id": "5a1iz510sv2W9Dt1MvFd5R",
            "name": "It's Beginning to Look a Lot like Christmas",
            "artist": "Michael Bubl\u00e9"
        },
        {
            "id": "7fDAriz5Ivea0Oy6VFuz4K",
            "name": "Ik ben een kerstbal",
            "artist": "Sesamstraat, Bert en Ernie"
        },
        {
            "id": "7taXf5odg9xCAZERYfyOkS",
            "name": "Feliz Navidad",
            "artist": "Jos\u00e9 Feliciano"
        }
    ],
    "unplayed_tracks": [
        {
            "id": "3pRaLNL3b8x5uBOcsgvdqM",
            "name": "Hallelujah",
            "artist": "Jeff Buckley"
        },
        {
            "id": "4wNl6yUAr6S81XlG4JCPB8",
            "name": "Why Couldn't It Be Christmas Everyday?",
            "artist": "Bianca Ryan"
        },
        {
            "id": "4VX8rdpYF4gVW4MXlIGkjh",
            "name": "Oh dennenboom",
            "artist": "Kinderliedjes Om Mee Te Zingen, Kerstliedjes Alles Kids"
        },
        {
            "id": "66clYwOMMBj6zBPZWdCOA0",
            "name": "Kerstmis",
            "artist": "Marco Borsato"
        },
        {
            "id": "3Z3QhZAZpqwZa1phsbQ3JZ",
            "name": "Driving Home for Christmas",
            "artist": "Chris Rea"
        },
        {
            "id": "3bH2Eu9A9ymI4UnGHRmoXg",
            "name": "Merry Christmas",
            "artist": "Ed Sheeran, Elton John"
        },
        {
            "id": "24yGxqQeuIZAp122sgzLXP",
            "name": "Santa's Party",
            "artist": "Nick & Simon"
        },
        {
            "id": "7z1WucYR62VIzGYeQTpEmF",
            "name": "KERST MET DE FAM",
            "artist": "MEROL"
        },
        {
            "id": "5gpImN0eqlucE3a3r121SF",
            "name": "Rockin' Around The Christmas Tree",
            "artist": "Mel & Kim"
        },
        {
            "id": "14tbD5Q9g4VymuAGnh9Tn1",
            "name": "Jingle Bells (Original Version)",
            "artist": "Christmas Party Stars"
        },
        {
            "id": "0247StOpd3AkeBQzANX4Zf",
            "name": "Do They Know It's Christmas? - 1984 Version",
            "artist": "Band Aid"
        },
        {
            "id": "4fzyvSu73BhGvi96p2zwjL",
            "name": "Christmas Lights",
            "artist": "Coldplay"
        }
    ],
    "cards": {
        "5ae89e26": {
            "tracks": [
                {
                    "id": "4wNl6yUAr6S81XlG4JCPB8",
                    "name": "Why Couldn't It Be Christmas Everyday?",
                    "artist": "Bianca Ryan"
                },
                {
                    "id": "7taXf5odg9xCAZERYfyOkS",
                    "name": "Feliz Navidad",
                    "artist": "Jos\u00e9 Feliciano"
                },
                {
                    "id": "0lizgQ7Qw35od7CYaoMBZb",
                    "name": "Santa Tell Me",
                    "artist": "Ariana Grande"
                },
                {
                    "id": "24yGxqQeuIZAp122sgzLXP",
                    "name": "Santa's Party",
                    "artist": "Nick & Simon"
                },
                {
                    "id": "1dSuhAiBjsrsUDzRsLKR3T",
                    "name": "Let It Snow",
                    "artist": "De Staat"
                },
                {
                    "id": "0QtJZpyfZF67QF32p41NXa",
                    "name": "Thank God It's Christmas",
                    "artist": "Queen"
                },
                {
                    "id": "5gpImN0eqlucE3a3r121SF",
                    "name": "Rockin' Around The Christmas Tree",
                    "artist": "Mel & Kim"
                },
                {
                    "id": "5UGAN5uZ8ic270gLaPaFBY",
                    "name": "Santa Claus Is Comin' to Town",
                    "artist": "Bruce Springsteen"
                },
                {
                    "id": "3Z3QhZAZpqwZa1phsbQ3JZ",
                    "name": "Driving Home for Christmas",
                    "artist": "Chris Rea"
                },
                {
                    "id": "3bH2Eu9A9ymI4UnGHRmoXg",
                    "name": "Merry Christmas",
                    "artist": "Ed Sheeran, Elton John"
                },
                {
                    "id": "4fzyvSu73BhGvi96p2zwjL",
                    "name": "Christmas Lights",
                    "artist": "Coldplay"
                },
                {
                    "id": "14tbD5Q9g4VymuAGnh9Tn1",
                    "name": "Jingle Bells (Original Version)",
                    "artist": "Christmas Party Stars"
                },
                {
                    "id": "0247StOpd3AkeBQzANX4Zf",
                    "name": "Do They Know It's Christmas? - 1984 Version",
                    "artist": "Band Aid"
                },
                {
                    "id": "66clYwOMMBj6zBPZWdCOA0",
                    "name": "Kerstmis",
                    "artist": "Marco Borsato"
                },
                {
                    "id": "2bCCJgTeIkO4BYqGoH2sPB",
                    "name": "Stille Nacht",
                    "artist": "Kinderliedjes, Kerstliedjes Band"
                },
                {
                    "id": "7fDAriz5Ivea0Oy6VFuz4K",
                    "name": "Ik ben een kerstbal",
                    "artist": "Sesamstraat, Bert en Ernie"
                },
                {
                    "id": "5a1iz510sv2W9Dt1MvFd5R",
                    "name": "It's Beginning to Look a Lot like Christmas",
                    "artist": "Michael Bubl\u00e9"
                },
                {
                    "id": "3ma7iAKJCYYIkNEjAmIyBA",
                    "name": "Being Alone At Christmas",
                    "artist": "Miss Montreal"
                },
                {
                    "id": "3pRaLNL3b8x5uBOcsgvdqM",
                    "name": "Hallelujah",
                    "artist": "Jeff Buckley"
                },
                {
                    "id": "2FRnf9qhLbvw8fu4IBXx78",
                    "name": "Last Christmas",
                    "artist": "Wham!"
                },
                {
                    "id": "4hAkwE0k1MlzDoOIf9J8ty",
                    "name": "Happy Xmas (War Is Over)",
                    "artist": "John Lennon, The Plastic Ono Band, The Harlem Community Choir"
                },
                {
                    "id": "2SpxCxwl7naL1IkcK1FlCU",
                    "name": "Ho Ho Ho",
                    "artist": "De Jeugd Van Tegenwoordig, Katja Schuurman"
                },
                {
                    "id": "7z1WucYR62VIzGYeQTpEmF",
                    "name": "KERST MET DE FAM",
                    "artist": "MEROL"
                },
                {
                    "id": "4VX8rdpYF4gVW4MXlIGkjh",
                    "name": "Oh dennenboom",
                    "artist": "Kinderliedjes Om Mee Te Zingen, Kerstliedjes Alles Kids"
                },
                {
                    "id": "66GRZWDfGCXCYql07FNZjk",
                    "name": "Het Is Pas Echt Kerstmis (Als Mariah Carey Op De Radio Is)",
                    "artist": "Vrienden Van De Frank En Vrijdag Show"
                }
            ],
            "bingo_status": "No bingo yet",
            "matches": [
                1,
                2,
                4,
                5,
                7,
                14,
                15,
                16,
                17,
                19,
                20,
                21,
                24
            ]
        },
        "20f794f8": {
            "tracks": [
                {
                    "id": "3bH2Eu9A9ymI4UnGHRmoXg",
                    "name": "Merry Christmas",
                    "artist": "Ed Sheeran, Elton John"
                },
                {
                    "id": "3ma7iAKJCYYIkNEjAmIyBA",
                    "name": "Being Alone At Christmas",
                    "artist": "Miss Montreal"
                },
                {
                    "id": "4wNl6yUAr6S81XlG4JCPB8",
                    "name": "Why Couldn't It Be Christmas Everyday?",
                    "artist": "Bianca Ryan"
                },
                {
                    "id": "2IuUMx3uxxJAHcH41aYtn0",
                    "name": "Winter Wonderland - Remastered 2006",
                    "artist": "Bing Crosby"
                },
                {
                    "id": "7fDAriz5Ivea0Oy6VFuz4K",
                    "name": "Ik ben een kerstbal",
                    "artist": "Sesamstraat, Bert en Ernie"
                },
                {
                    "id": "66GRZWDfGCXCYql07FNZjk",
                    "name": "Het Is Pas Echt Kerstmis (Als Mariah Carey Op De Radio Is)",
                    "artist": "Vrienden Van De Frank En Vrijdag Show"
                },
                {
                    "id": "0247StOpd3AkeBQzANX4Zf",
                    "name": "Do They Know It's Christmas? - 1984 Version",
                    "artist": "Band Aid"
                },
                {
                    "id": "4hAkwE0k1MlzDoOIf9J8ty",
                    "name": "Happy Xmas (War Is Over)",
                    "artist": "John Lennon, The Plastic Ono Band, The Harlem Community Choir"
                },
                {
                    "id": "24yGxqQeuIZAp122sgzLXP",
                    "name": "Santa's Party",
                    "artist": "Nick & Simon"
                },
                {
                    "id": "2FRnf9qhLbvw8fu4IBXx78",
                    "name": "Last Christmas",
                    "artist": "Wham!"
                },
                {
                    "id": "3Z3QhZAZpqwZa1phsbQ3JZ",
                    "name": "Driving Home for Christmas",
                    "artist": "Chris Rea"
                },
                {
                    "id": "5gpImN0eqlucE3a3r121SF",
                    "name": "Rockin' Around The Christmas Tree",
                    "artist": "Mel & Kim"
                },
                {
                    "id": "0bYg9bo50gSsH3LtXe2SQn",
                    "name": "All I Want for Christmas Is You",
                    "artist": "Mariah Carey"
                },
                {
                    "id": "14tbD5Q9g4VymuAGnh9Tn1",
                    "name": "Jingle Bells (Original Version)",
                    "artist": "Christmas Party Stars"
                },
                {
                    "id": "2SpxCxwl7naL1IkcK1FlCU",
                    "name": "Ho Ho Ho",
                    "artist": "De Jeugd Van Tegenwoordig, Katja Schuurman"
                },
                {
                    "id": "3pRaLNL3b8x5uBOcsgvdqM",
                    "name": "Hallelujah",
                    "artist": "Jeff Buckley"
                },
                {
                    "id": "7z1WucYR62VIzGYeQTpEmF",
                    "name": "KERST MET DE FAM",
                    "artist": "MEROL"
                },
                {
                    "id": "1dSuhAiBjsrsUDzRsLKR3T",
                    "name": "Let It Snow",
                    "artist": "De Staat"
                },
                {
                    "id": "7taXf5odg9xCAZERYfyOkS",
                    "name": "Feliz Navidad",
                    "artist": "Jos\u00e9 Feliciano"
                },
                {
                    "id": "5UGAN5uZ8ic270gLaPaFBY",
                    "name": "Santa Claus Is Comin' to Town",
                    "artist": "Bruce Springsteen"
                },
                {
                    "id": "2bCCJgTeIkO4BYqGoH2sPB",
                    "name": "Stille Nacht",
                    "artist": "Kinderliedjes, Kerstliedjes Band"
                },
                {
                    "id": "0lizgQ7Qw35od7CYaoMBZb",
                    "name": "Santa Tell Me",
                    "artist": "Ariana Grande"
                },
                {
                    "id": "0QtJZpyfZF67QF32p41NXa",
                    "name": "Thank God It's Christmas",
                    "artist": "Queen"
                },
                {
                    "id": "5a1iz510sv2W9Dt1MvFd5R",
                    "name": "It's Beginning to Look a Lot like Christmas",
                    "artist": "Michael Bubl\u00e9"
                },
                {
                    "id": "4fzyvSu73BhGvi96p2zwjL",
                    "name": "Christmas Lights",
                    "artist": "Coldplay"
                }
            ],
            "bingo_status": "No bingo yet",
            "matches": [
                1,
                3,
                4,
                5,
                7,
                9,
                12,
                14,
                17,
                18,
                19,
                20,
                21,
                22,
                23
            ]
        },
        "262a91c1": {
            "tracks": [
                {
                    "id": "0QtJZpyfZF67QF32p41NXa",
                    "name": "Thank God It's Christmas",
                    "artist": "Queen"
                },
                {
                    "id": "3Z3QhZAZpqwZa1phsbQ3JZ",
                    "name": "Driving Home for Christmas",
                    "artist": "Chris Rea"
                },
                {
                    "id": "7taXf5odg9xCAZERYfyOkS",
                    "name": "Feliz Navidad",
                    "artist": "Jos\u00e9 Feliciano"
                },
                {
                    "id": "4wNl6yUAr6S81XlG4JCPB8",
                    "name": "Why Couldn't It Be Christmas Everyday?",
                    "artist": "Bianca Ryan"
                },
                {
                    "id": "5a1iz510sv2W9Dt1MvFd5R",
                    "name": "It's Beginning to Look a Lot like Christmas",
                    "artist": "Michael Bubl\u00e9"
                },
                {
                    "id": "5UGAN5uZ8ic270gLaPaFBY",
                    "name": "Santa Claus Is Comin' to Town",
                    "artist": "Bruce Springsteen"
                },
                {
                    "id": "2SpxCxwl7naL1IkcK1FlCU",
                    "name": "Ho Ho Ho",
                    "artist": "De Jeugd Van Tegenwoordig, Katja Schuurman"
                },
                {
                    "id": "2bCCJgTeIkO4BYqGoH2sPB",
                    "name": "Stille Nacht",
                    "artist": "Kinderliedjes, Kerstliedjes Band"
                },
                {
                    "id": "14tbD5Q9g4VymuAGnh9Tn1",
                    "name": "Jingle Bells (Original Version)",
                    "artist": "Christmas Party Stars"
                },
                {
                    "id": "2IuUMx3uxxJAHcH41aYtn0",
                    "name": "Winter Wonderland - Remastered 2006",
                    "artist": "Bing Crosby"
                },
                {
                    "id": "0247StOpd3AkeBQzANX4Zf",
                    "name": "Do They Know It's Christmas? - 1984 Version",
                    "artist": "Band Aid"
                },
                {
                    "id": "3pRaLNL3b8x5uBOcsgvdqM",
                    "name": "Hallelujah",
                    "artist": "Jeff Buckley"
                },
                {
                    "id": "2FRnf9qhLbvw8fu4IBXx78",
                    "name": "Last Christmas",
                    "artist": "Wham!"
                },
                {
                    "id": "0lizgQ7Qw35od7CYaoMBZb",
                    "name": "Santa Tell Me",
                    "artist": "Ariana Grande"
                },
                {
                    "id": "0bYg9bo50gSsH3LtXe2SQn",
                    "name": "All I Want for Christmas Is You",
                    "artist": "Mariah Carey"
                },
                {
                    "id": "4fzyvSu73BhGvi96p2zwjL",
                    "name": "Christmas Lights",
                    "artist": "Coldplay"
                },
                {
                    "id": "7fDAriz5Ivea0Oy6VFuz4K",
                    "name": "Ik ben een kerstbal",
                    "artist": "Sesamstraat, Bert en Ernie"
                },
                {
                    "id": "3ma7iAKJCYYIkNEjAmIyBA",
                    "name": "Being Alone At Christmas",
                    "artist": "Miss Montreal"
                },
                {
                    "id": "5gpImN0eqlucE3a3r121SF",
                    "name": "Rockin' Around The Christmas Tree",
                    "artist": "Mel & Kim"
                },
                {
                    "id": "4VX8rdpYF4gVW4MXlIGkjh",
                    "name": "Oh dennenboom",
                    "artist": "Kinderliedjes Om Mee Te Zingen, Kerstliedjes Alles Kids"
                },
                {
                    "id": "66clYwOMMBj6zBPZWdCOA0",
                    "name": "Kerstmis",
                    "artist": "Marco Borsato"
                },
                {
                    "id": "3bH2Eu9A9ymI4UnGHRmoXg",
                    "name": "Merry Christmas",
                    "artist": "Ed Sheeran, Elton John"
                },
                {
                    "id": "66GRZWDfGCXCYql07FNZjk",
                    "name": "Het Is Pas Echt Kerstmis (Als Mariah Carey Op De Radio Is)",
                    "artist": "Vrienden Van De Frank En Vrijdag Show"
                },
                {
                    "id": "4hAkwE0k1MlzDoOIf9J8ty",
                    "name": "Happy Xmas (War Is Over)",
                    "artist": "John Lennon, The Plastic Ono Band, The Harlem Community Choir"
                },
                {
                    "id": "7z1WucYR62VIzGYeQTpEmF",
                    "name": "KERST MET DE FAM",
                    "artist": "MEROL"
                }
            ],
            "bingo_status": "BINGO!",
            "matches": [
                0,
                2,
                4,
                5,
                6,
                7,
                9,
                12,
                13,
                14,
                16,
                17,
                22,
                23
            ]
        },
        "2ff60579": {
            "tracks": [
                {
                    "id": "4fzyvSu73BhGvi96p2zwjL",
                    "name": "Christmas Lights",
                    "artist": "Coldplay"
                },
                {
                    "id": "3bH2Eu9A9ymI4UnGHRmoXg",
                    "name": "Merry Christmas",
                    "artist": "Ed Sheeran, Elton John"
                },
                {
                    "id": "2IuUMx3uxxJAHcH41aYtn0",
                    "name": "Winter Wonderland - Remastered 2006",
                    "artist": "Bing Crosby"
                },
                {
                    "id": "3pRaLNL3b8x5uBOcsgvdqM",
                    "name": "Hallelujah",
                    "artist": "Jeff Buckley"
                },
                {
                    "id": "3ma7iAKJCYYIkNEjAmIyBA",
                    "name": "Being Alone At Christmas",
                    "artist": "Miss Montreal"
                },
                {
                    "id": "0247StOpd3AkeBQzANX4Zf",
                    "name": "Do They Know It's Christmas? - 1984 Version",
                    "artist": "Band Aid"
                },
                {
                    "id": "4hAkwE0k1MlzDoOIf9J8ty",
                    "name": "Happy Xmas (War Is Over)",
                    "artist": "John Lennon, The Plastic Ono Band, The Harlem Community Choir"
                },
                {
                    "id": "14tbD5Q9g4VymuAGnh9Tn1",
                    "name": "Jingle Bells (Original Version)",
                    "artist": "Christmas Party Stars"
                },
                {
                    "id": "7taXf5odg9xCAZERYfyOkS",
                    "name": "Feliz Navidad",
                    "artist": "Jos\u00e9 Feliciano"
                },
                {
                    "id": "5UGAN5uZ8ic270gLaPaFBY",
                    "name": "Santa Claus Is Comin' to Town",
                    "artist": "Bruce Springsteen"
                },
                {
                    "id": "5a1iz510sv2W9Dt1MvFd5R",
                    "name": "It's Beginning to Look a Lot like Christmas",
                    "artist": "Michael Bubl\u00e9"
                },
                {
                    "id": "0bYg9bo50gSsH3LtXe2SQn",
                    "name": "All I Want for Christmas Is You",
                    "artist": "Mariah Carey"
                },
                {
                    "id": "66clYwOMMBj6zBPZWdCOA0",
                    "name": "Kerstmis",
                    "artist": "Marco Borsato"
                },
                {
                    "id": "3Z3QhZAZpqwZa1phsbQ3JZ",
                    "name": "Driving Home for Christmas",
                    "artist": "Chris Rea"
                },
                {
                    "id": "5gpImN0eqlucE3a3r121SF",
                    "name": "Rockin' Around The Christmas Tree",
                    "artist": "Mel & Kim"
                },
                {
                    "id": "24yGxqQeuIZAp122sgzLXP",
                    "name": "Santa's Party",
                    "artist": "Nick & Simon"
                },
                {
                    "id": "2SpxCxwl7naL1IkcK1FlCU",
                    "name": "Ho Ho Ho",
                    "artist": "De Jeugd Van Tegenwoordig, Katja Schuurman"
                },
                {
                    "id": "66GRZWDfGCXCYql07FNZjk",
                    "name": "Het Is Pas Echt Kerstmis (Als Mariah Carey Op De Radio Is)",
                    "artist": "Vrienden Van De Frank En Vrijdag Show"
                },
                {
                    "id": "7z1WucYR62VIzGYeQTpEmF",
                    "name": "KERST MET DE FAM",
                    "artist": "MEROL"
                },
                {
                    "id": "0QtJZpyfZF67QF32p41NXa",
                    "name": "Thank God It's Christmas",
                    "artist": "Queen"
                },
                {
                    "id": "2FRnf9qhLbvw8fu4IBXx78",
                    "name": "Last Christmas",
                    "artist": "Wham!"
                },
                {
                    "id": "0lizgQ7Qw35od7CYaoMBZb",
                    "name": "Santa Tell Me",
                    "artist": "Ariana Grande"
                },
                {
                    "id": "2bCCJgTeIkO4BYqGoH2sPB",
                    "name": "Stille Nacht",
                    "artist": "Kinderliedjes, Kerstliedjes Band"
                },
                {
                    "id": "4wNl6yUAr6S81XlG4JCPB8",
                    "name": "Why Couldn't It Be Christmas Everyday?",
                    "artist": "Bianca Ryan"
                },
                {
                    "id": "7fDAriz5Ivea0Oy6VFuz4K",
                    "name": "Ik ben een kerstbal",
                    "artist": "Sesamstraat, Bert en Ernie"
                }
            ],
            "bingo_status": "No bingo yet",
            "matches": [
                2,
                4,
                6,
                8,
                9,
                10,
                11,
                16,
                17,
                19,
                20,
                21,
                22,
                24
            ]
        }
    },
    "bingo_mode": "rowcoldiag",
    "current_playlist": "https://open.spotify.com/playlist/7jGLlHSJum8EpoXc9uTRGa?si=8bbf353901c84e7a",
    "num_tracks": 27
}